[
  {
    "title": "My Best Friend Who I Love Fell Completely in Love With My Vtuber Self",
    "url": "https://mangareader.to/my-best-friend-who-i-love-fell-completely-in-love-with-my-vtuber-self-57676",
    "cover_url": "https://img.mreadercdn.com/_m/300x400/100/e6/db/e6db016b95b5f99adf4bdea7b494fff8/e6db016b95b5f99adf4bdea7b494fff8.jpg",
    "synopsis": "Not available",
    "author": [
      "Unknown"
    ],
    "genres": [
      "Comedy",
      "Romance"
    ],
    "rating": null,
    "status": "Unknown"
  },
  {
    "title": "My BFF is a Tyrant in Training",
    "url": "https://mangareader.to/my-bff-is-a-tyrant-in-training-58126",
    "cover_url": "https://img.mreadercdn.com/_m/300x400/100/19/bc/19bcfbc68ab200195648d4c088cccaa8/19bcfbc68ab200195648d4c088cccaa8.jpg",
    "synopsis": "Not available",
    "author": [
      "Unknown"
    ],
    "genres": [
      "Adventure",
      "Drama",
      "Fantasy",
      "Magic",
      "Romance"
    ],
    "rating": null,
    "status": "Unknown"
  },
  {
    "title": "My big boss daddy’s",
    "url": "https://mangareader.to/my-big-boss-daddys-63930",
    "cover_url": "https://img.mreadercdn.com/_m/300x400/100/2a/24/2a243f9d2b085ecd9377dd7ad5fbaea2/2a243f9d2b085ecd9377dd7ad5fbaea2.jpg",
    "synopsis": "Not available",
    "author": [
      "Unknown"
    ],
    "genres": [
      "Comedy",
      "Harem",
      "Historical"
    ],
    "rating": null,
    "status": "Unknown"
  },
  {
    "title": "My Big Sister Arrived",
    "url": "https://mangareader.to/my-big-sister-arrived-7869",
    "cover_url": "https://img.mreadercdn.com/_m/300x400/100/1a/a9/1aa9751bf8b4c5650c4a52bd1c164264/1aa9751bf8b4c5650c4a52bd1c164264.jpg",
    "synopsis": "Not available",
    "author": [
      "Unknown"
    ],
    "genres": [
      "Comedy",
      "Slice of Life"
    ],
    "rating": null,
    "status": "Unknown"
  },
  {
    "title": "My Big Sister Is A Love Youkai",
    "url": "https://mangareader.to/my-big-sister-is-a-love-youkai-12769",
    "cover_url": "https://img.mreadercdn.com/_m/300x400/100/e6/99/e699f6300937e09bf33fba01295ee290/e699f6300937e09bf33fba01295ee290.jpg",
    "synopsis": "Not available",
    "author": [
      "Unknown"
    ],
    "genres": [
      "Ecchi",
      "Harem",
      "Romance",
      "Supernatural"
    ],
    "rating": null,
    "status": "Unknown"
  },
  {
    "title": "My Black Mage Is Too Cute!",
    "url": "https://mangareader.to/my-black-mage-is-too-cute-67919",
    "cover_url": "https://img.mreadercdn.com/_m/300x400/100/ed/b6/edb6a1552607cd4f672c829246eef1f4/edb6a1552607cd4f672c829246eef1f4.jpg",
    "synopsis": "Not available",
    "author": [
      "Unknown"
    ],
    "genres": [
      "Comedy",
      "Fantasy",
      "Magic",
      "Romance",
      "School"
    ],
    "rating": null,
    "status": "Unknown"
  },
  {
    "title": "My Blade Will Lead the Way! Abandoned in a Labyrinth as a Directionally Challenged S-Rank Swordsman",
    "url": "https://mangareader.to/my-blade-will-lead-the-way-abandoned-in-a-labyrinth-as-a-directionally-challenged-s-rank-swordsman-67493",
    "cover_url": "https://img.mreadercdn.com/_m/300x400/100/fd/d6/fdd6c181c866c2e8c977130bf286d6fe/fdd6c181c866c2e8c977130bf286d6fe.jpg",
    "synopsis": "Not available",
    "author": [
      "Unknown"
    ],
    "genres": [
      "Adventure",
      "Comedy",
      "Fantasy",
      "Shounen"
    ],
    "rating": null,
    "status": "Unknown"
  },
  {
    "title": "My Blind Date Is A Womanizing Cop",
    "url": "https://mangareader.to/my-blind-date-is-a-womanizing-cop-36661",
    "cover_url": "https://img.mreadercdn.com/_m/300x400/100/23/0a/230a32577fba9f9d0eb64b80bf6e3379/230a32577fba9f9d0eb64b80bf6e3379.jpg",
    "synopsis": "Not available",
    "author": [
      "Unknown"
    ],
    "genres": [
      "Comedy",
      "Romance"
    ],
    "rating": null,
    "status": "Unknown"
  },
  {
    "title": "My Blissful Marriage",
    "url": "https://mangareader.to/my-blissful-marriage-1950",
    "cover_url": "https://img.mreadercdn.com/_m/300x400/100/4a/22/4a228ba407062bcc1851044aa8dbb9ac/4a228ba407062bcc1851044aa8dbb9ac.jpg",
    "synopsis": "Not available",
    "author": [
      "Unknown"
    ],
    "genres": [
      "Drama",
      "Historical",
      "Romance"
    ],
    "rating": null,
    "status": "Unknown"
  },
  {
    "title": "My Boo",
    "url": "https://mangareader.to/my-boo-1421",
    "cover_url": "https://img.mreadercdn.com/_m/300x400/100/06/2b/062b58e3ed7863a3e1d82fc4d83e8b9e/062b58e3ed7863a3e1d82fc4d83e8b9e.jpg",
    "synopsis": "Not available",
    "author": [
      "Unknown"
    ],
    "genres": [
      "Drama",
      "Psychological",
      "Romance",
      "Supernatural"
    ],
    "rating": null,
    "status": "Unknown"
  },
  {
    "title": "My Borrowed Body",
    "url": "https://mangareader.to/my-borrowed-body-57048",
    "cover_url": "https://img.mreadercdn.com/_m/300x400/100/76/51/765108353d733745fde2460d5b92e719/765108353d733745fde2460d5b92e719.jpg",
    "synopsis": "Not available",
    "author": [
      "Unknown"
    ],
    "genres": [
      "Romance",
      "School"
    ],
    "rating": null,
    "status": "Unknown"
  },
  {
    "title": "My Boss",
    "url": "https://mangareader.to/my-boss-56015",
    "cover_url": "https://img.mreadercdn.com/_m/300x400/100/28/42/2842e3544af84a45f7e8ee99dbe3c833/2842e3544af84a45f7e8ee99dbe3c833.png",
    "synopsis": "Not available",
    "author": [
      "Unknown"
    ],
    "genres": [
      "Romance",
      "Shoujo"
    ],
    "rating": null,
    "status": "Unknown"
  },
  {
    "title": "My Boss Is A Goddess",
    "url": "https://mangareader.to/my-boss-is-a-goddess-64649",
    "cover_url": "https://img.mreadercdn.com/_m/300x400/100/57/df/57df1fb62f3c561ad9a82707c3f468b1/57df1fb62f3c561ad9a82707c3f468b1.jpg",
    "synopsis": "Not available",
    "author": [
      "Unknown"
    ],
    "genres": [
      "Comedy",
      "Drama",
      "Romance",
      "Shounen Ai"
    ],
    "rating": null,
    "status": "Unknown"
  },
  {
    "title": "My Boss's Kitten",
    "url": "https://mangareader.to/my-bosss-kitten-8384",
    "cover_url": "https://img.mreadercdn.com/_m/300x400/100/1e/47/1e4749c6c4e14efb78cd8f8106472a25/1e4749c6c4e14efb78cd8f8106472a25.jpg",
    "synopsis": "Not available",
    "author": [
      "Unknown"
    ],
    "genres": [
      "Romance",
      "Shoujo"
    ],
    "rating": null,
    "status": "Unknown"
  },
  {
    "title": "My Boy",
    "url": "https://mangareader.to/my-boy-820",
    "cover_url": "https://img.mreadercdn.com/_m/300x400/100/22/12/221273ac7ef485be188bb46363004b21/221273ac7ef485be188bb46363004b21.jpg",
    "synopsis": "Not available",
    "author": [
      "Unknown"
    ],
    "genres": [
      "Drama",
      "Seinen"
    ],
    "rating": null,
    "status": "Unknown"
  },
  {
    "title": "My Boy in Blue",
    "url": "https://mangareader.to/my-boy-in-blue-2426",
    "cover_url": "https://img.mreadercdn.com/_m/300x400/100/96/1c/961ca61c17ee6d34d0374e7ca4218480/961ca61c17ee6d34d0374e7ca4218480.jpg",
    "synopsis": "Not available",
    "author": [
      "Unknown"
    ],
    "genres": [
      "Romance",
      "Shoujo"
    ],
    "rating": null,
    "status": "Unknown"
  },
  {
    "title": "My Boyfriend in Orange",
    "url": "https://mangareader.to/my-boyfriend-in-orange-3435",
    "cover_url": "https://img.mreadercdn.com/_m/300x400/100/12/97/12979f7d667536040e4fe5484dea25a2/12979f7d667536040e4fe5484dea25a2.jpg",
    "synopsis": "Not available",
    "author": [
      "Unknown"
    ],
    "genres": [
      "Romance",
      "Shoujo"
    ],
    "rating": null,
    "status": "Unknown"
  },
  {
    "title": "My Boyfriend is a Jinyiwei",
    "url": "https://mangareader.to/my-boyfriend-is-a-jinyiwei-60158",
    "cover_url": "https://img.mreadercdn.com/_m/300x400/100/ab/44/ab44a40905ec62d9995d69ac9548797e/ab44a40905ec62d9995d69ac9548797e.jpg",
    "synopsis": "Not available",
    "author": [
      "Unknown"
    ],
    "genres": [
      "Drama",
      "Historical",
      "Romance",
      "Shoujo"
    ],
    "rating": null,
    "status": "Unknown"
  }
]