[
  {
    "title": "Reijou Kishi wa Tenseisha",
    "url": "https://mangareader.to/reijou-kishi-wa-tenseisha-65195",
    "cover_url": "https://img.mreadercdn.com/_m/300x400/100/6d/5f/6d5f02534b7a7d2af71917aabaf4fff4/6d5f02534b7a7d2af71917aabaf4fff4.jpg",
    "synopsis": "Not available",
    "author": [
      "Unknown"
    ],
    "genres": [
      "Fantasy",
      "Josei",
      "Romance"
    ],
    "rating": null,
    "status": "Unknown"
  },
  {
    "title": "Reiko the Zombie Shop",
    "url": "https://mangareader.to/reiko-the-zombie-shop-5553",
    "cover_url": "https://img.mreadercdn.com/_m/300x400/100/4e/89/4e89732172705806f3b754df2b0ed993/4e89732172705806f3b754df2b0ed993.jpg",
    "synopsis": "Not available",
    "author": [
      "Unknown"
    ],
    "genres": [
      "Horror",
      "Josei"
    ],
    "rating": null,
    "status": "Unknown"
  },
  {
    "title": "Reikoku Shitsuji wa Maid wo Dekiai suru",
    "url": "https://mangareader.to/reikoku-shitsuji-wa-maid-wo-dekiai-suru-59958",
    "cover_url": "https://img.mreadercdn.com/_m/300x400/100/69/d0/69d00abc65ece6e56b8f97d2b7595e97/69d00abc65ece6e56b8f97d2b7595e97.jpg",
    "synopsis": "Not available",
    "author": [
      "Unknown"
    ],
    "genres": [
      "Drama",
      "Josei",
      "Romance"
    ],
    "rating": null,
    "status": "Unknown"
  },
  {
    "title": "Reincarnate and Live in a Different World Doing What You Love While Being Liked by Everything",
    "url": "https://mangareader.to/reincarnate-and-live-in-a-different-world-doing-what-you-love-while-being-liked-by-everything-67195",
    "cover_url": "https://img.mreadercdn.com/_m/300x400/100/06/41/064126d2e32b58af3870539f39b137a6/064126d2e32b58af3870539f39b137a6.jpg",
    "synopsis": "Not available",
    "author": [
      "Unknown"
    ],
    "genres": [
      "Comedy",
      "Fantasy",
      "Seinen",
      "Slice of Life"
    ],
    "rating": null,
    "status": "Unknown"
  },
  {
    "title": "Reincarnated Adventurer of the Curse Mark",
    "url": "https://mangareader.to/reincarnated-adventurer-of-the-curse-mark-65019",
    "cover_url": "https://img.mreadercdn.com/_m/300x400/100/43/4d/434de26c63a315bbae9ff32c83a72caf/434de26c63a315bbae9ff32c83a72caf.jpg",
    "synopsis": "Not available",
    "author": [
      "Unknown"
    ],
    "genres": [
      "Action",
      "Adventure",
      "Comedy",
      "Fantasy",
      "Romance"
    ],
    "rating": null,
    "status": "Unknown"
  },
  {
    "title": "Reincarnated as a Dragon Hatchling",
    "url": "https://mangareader.to/reincarnated-as-a-dragon-hatchling-6220",
    "cover_url": "https://img.mreadercdn.com/_m/300x400/100/85/10/85104426cdccfff1030ab8ea83badd28/85104426cdccfff1030ab8ea83badd28.jpg",
    "synopsis": "Not available",
    "author": [
      "Unknown"
    ],
    "genres": [
      "Action",
      "Adventure",
      "Fantasy"
    ],
    "rating": null,
    "status": "Unknown"
  },
  {
    "title": "Reincarnated as a Poor Farmer in Another World, so He Decided to Make Bricks and Build a Castle",
    "url": "https://mangareader.to/reincarnated-as-a-poor-farmer-in-another-world-so-he-decided-to-make-bricks-and-build-a-castle-64573",
    "cover_url": "https://img.mreadercdn.com/_m/300x400/100/1e/62/1e6201be1a021a58e0816a06f825ef5f/1e6201be1a021a58e0816a06f825ef5f.jpg",
    "synopsis": "Not available",
    "author": [
      "Unknown"
    ],
    "genres": [
      "Adventure",
      "Comedy",
      "Drama",
      "Fantasy",
      "Shounen",
      "Slice of Life"
    ],
    "rating": null,
    "status": "Unknown"
  },
  {
    "title": "Reincarnated As a Racehorse",
    "url": "https://mangareader.to/reincarnated-as-a-racehorse-50210",
    "cover_url": "https://img.mreadercdn.com/_m/300x400/100/66/dd/66dd7488c953d63c814ec8e0f60dbfda/66dd7488c953d63c814ec8e0f60dbfda.jpg",
    "synopsis": "Not available",
    "author": [
      "Unknown"
    ],
    "genres": [
      "Comedy",
      "Ecchi",
      "Fantasy",
      "Romance",
      "Sports"
    ],
    "rating": null,
    "status": "Unknown"
  },
  {
    "title": "Reincarnated as a Sword",
    "url": "https://mangareader.to/reincarnated-as-a-sword-2150",
    "cover_url": "https://img.mreadercdn.com/_m/300x400/100/b0/05/b005e2206f07beecc44880daf42af575/b005e2206f07beecc44880daf42af575.jpg",
    "synopsis": "Not available",
    "author": [
      "Unknown"
    ],
    "genres": [
      "Action",
      "Adventure",
      "Comedy",
      "Fantasy"
    ],
    "rating": null,
    "status": "Unknown"
  },
  {
    "title": "Reincarnated as a the strongest wand, I'm forcing a girl who hates me to be a magical girl",
    "url": "https://mangareader.to/reincarnated-as-a-the-strongest-wand-im-forcing-a-girl-who-hates-me-to-be-a-magical-girl-13358",
    "cover_url": "https://img.mreadercdn.com/_m/300x400/100/05/32/05320b1edec164b08ad7e36dde0de124/05320b1edec164b08ad7e36dde0de124.jpg",
    "synopsis": "Not available",
    "author": [
      "Unknown"
    ],
    "genres": [
      "Comedy",
      "Ecchi",
      "Fantasy"
    ],
    "rating": null,
    "status": "Unknown"
  },
  {
    "title": "Reincarnated as a Villager ~ Strongest Slow-Life",
    "url": "https://mangareader.to/reincarnated-as-a-villager-strongest-slow-life-13140",
    "cover_url": "https://img.mreadercdn.com/_m/300x400/100/25/a6/25a6a2ce079891551b6cab1522c5acd5/25a6a2ce079891551b6cab1522c5acd5.jpg",
    "synopsis": "Not available",
    "author": [
      "Unknown"
    ],
    "genres": [
      "Action",
      "Adventure",
      "Comedy",
      "Seinen",
      "Slice of Life"
    ],
    "rating": null,
    "status": "Unknown"
  },
  {
    "title": "Reincarnated as a Villainess's Brother",
    "url": "https://mangareader.to/reincarnated-as-a-villainesss-brother-58334",
    "cover_url": "https://img.mreadercdn.com/_m/300x400/100/b8/8f/b88f9d3e89bf714adf3128dd445b5389/b88f9d3e89bf714adf3128dd445b5389.jpg",
    "synopsis": "Not available",
    "author": [
      "Unknown"
    ],
    "genres": [
      "Comedy",
      "Fantasy",
      "Romance",
      "Slice of Life"
    ],
    "rating": null,
    "status": "Unknown"
  },
  {
    "title": "Reincarnated as an Aristocrat with an Appraisal Skill",
    "url": "https://mangareader.to/reincarnated-as-an-aristocrat-with-an-appraisal-skill-11365",
    "cover_url": "https://img.mreadercdn.com/_m/300x400/100/fd/5d/fd5de137f3522f206e13995e608f5bc7/fd5de137f3522f206e13995e608f5bc7.jpg",
    "synopsis": "Not available",
    "author": [
      "Unknown"
    ],
    "genres": [
      "Adventure",
      "Fantasy"
    ],
    "rating": null,
    "status": "Unknown"
  },
  {
    "title": "Reincarnated as an Immortal: I'm Scum but I'm Peerless With Regeneration Cheats",
    "url": "https://mangareader.to/reincarnated-as-an-immortal-im-scum-but-im-peerless-with-regeneration-cheats-65089",
    "cover_url": "https://img.mreadercdn.com/_m/300x400/100/a4/be/a4be42a4ecdf6b3462d365ef91fca2d3/a4be42a4ecdf6b3462d365ef91fca2d3.jpg",
    "synopsis": "Not available",
    "author": [
      "Unknown"
    ],
    "genres": [
      "Fantasy"
    ],
    "rating": null,
    "status": "Unknown"
  },
  {
    "title": "Reincarnated as an Overly Timid Countess",
    "url": "https://mangareader.to/reincarnated-as-an-overly-timid-countess-65531",
    "cover_url": "https://img.mreadercdn.com/_m/300x400/100/ad/50/ad50e20c314e486e63708213357c8a32/ad50e20c314e486e63708213357c8a32.jpg",
    "synopsis": "Not available",
    "author": [
      "Unknown"
    ],
    "genres": [
      "Fantasy",
      "Romance"
    ],
    "rating": null,
    "status": "Unknown"
  },
  {
    "title": "Reincarnated as Louis XVI, I want to stop the French Revolution with all my might and live happily ever after with Antoinette",
    "url": "https://mangareader.to/reincarnated-as-louis-xvi-i-want-to-stop-the-french-revolution-with-all-my-might-and-live-happily-ever-after-with-antoinette-60566",
    "cover_url": "https://img.mreadercdn.com/_m/300x400/100/5d/21/5d2100ee5adcb5fb58f6cfbff847dd64/5d2100ee5adcb5fb58f6cfbff847dd64.jpg",
    "synopsis": "Not available",
    "author": [
      "Unknown"
    ],
    "genres": [
      "Comedy",
      "Historical",
      "Romance"
    ],
    "rating": null,
    "status": "Unknown"
  },
  {
    "title": "Reincarnated as the Mastermind of the Story",
    "url": "https://mangareader.to/reincarnated-as-the-mastermind-of-the-story-63010",
    "cover_url": "https://img.mreadercdn.com/_m/300x400/100/db/13/db1377caa03d33a1ddcb7b3961b80c75/db1377caa03d33a1ddcb7b3961b80c75.jpg",
    "synopsis": "Not available",
    "author": [
      "Unknown"
    ],
    "genres": [
      "Fantasy",
      "Romance",
      "Shounen"
    ],
    "rating": null,
    "status": "Unknown"
  },
  {
    "title": "Reincarnated as the Most Hated Villain",
    "url": "https://mangareader.to/reincarnated-as-the-most-hated-villain-68431",
    "cover_url": "https://img.mreadercdn.com/_m/300x400/100/1e/36/1e361c5aeec21e00db40e16bf21c47bd/1e361c5aeec21e00db40e16bf21c47bd.jpg",
    "synopsis": "Not available",
    "author": [
      "Unknown"
    ],
    "genres": [
      "Action",
      "Fantasy"
    ],
    "rating": null,
    "status": "Unknown"
  }
]