[
  {
    "title": "Tianbao Fuyao Lu",
    "url": "https://mangareader.to/tianbao-fuyao-lu-60596",
    "cover_url": "https://img.mreadercdn.com/_m/300x400/100/48/30/4830a31f91b49f5e8272dbe4bc0f504e/4830a31f91b49f5e8272dbe4bc0f504e.jpg",
    "synopsis": "Not available",
    "author": [
      "Unknown"
    ],
    "genres": [
      "Action",
      "Adventure",
      "Comedy",
      "Fantasy",
      "Historical",
      "Romance",
      "Shounen Ai",
      "Yaoi"
    ],
    "rating": null,
    "status": "Unknown"
  },
  {
    "title": "Tickle Town",
    "url": "https://mangareader.to/tickle-town-60616",
    "cover_url": "https://img.mreadercdn.com/_m/300x400/100/f0/08/f0085852b2ca03bd9f8b8cc468312566/f0085852b2ca03bd9f8b8cc468312566.jpg",
    "synopsis": "Not available",
    "author": [
      "Unknown"
    ],
    "genres": [
      "",
      "Genres\n\n\n\n\n\n\n\n\n⚡\n            Latest Updated\n✌ New Release\n🔥\n            Most Viewed\n✅\n            Completed\n\n\n\nAction\n\n\nAdventure\n\n\nCars\n\n\nComedy\n\n\nDementia\n\n\nDemons\n\n\nDoujinshi\n\n\nDrama\n\n\nEcchi\n\n\nFantasy\n\n\nGame\n\n\nGender Bender\n\n\nHarem\n\n\nHentai\n\n\nHistorical\n\n\nHorror\n\n\nJosei\n\n\nKids\n\n\nMagic\n\n\nMartial Arts\n\n\nMecha\n\n\nMilitary\n\n\nMusic\n\n\nMystery\n\n\nParody\n\n\nPolice\n\n\nPsychological\n\n\nRomance\n\n\nSamurai\n\n\nSchool\n\n\nSci-Fi\n\n\nSeinen\n\n\nShoujo\n\n\nShoujo Ai\n\n\nShounen\n\n\nShounen Ai\n\n\nSlice of Life\n\n\nSpace\n\n\nSports\n\n\nSuper Power\n\n\nSupernatural\n\n\nThriller\n\n\nVampire\n\n\nYaoi\n\n\nYuri\n\n+ More"
    ],
    "rating": null,
    "status": "Unknown"
  },
  {
    "title": "Tiempo",
    "url": "https://mangareader.to/tiempo-34035",
    "cover_url": "https://img.mreadercdn.com/_m/300x400/100/d7/58/d758d7cff89f060a2991d0b51d78be17/d758d7cff89f060a2991d0b51d78be17.jpg",
    "synopsis": "Not available",
    "author": [
      "Unknown"
    ],
    "genres": [
      "School",
      "Seinen",
      "Sports"
    ],
    "rating": null,
    "status": "Unknown"
  },
  {
    "title": "Tiger & Bunny 2: The Comic",
    "url": "https://mangareader.to/tiger-bunny-2-the-comic-64353",
    "cover_url": "https://img.mreadercdn.com/_m/300x400/100/5b/22/5b22e86761d546e5596c35ceea6e0f34/5b22e86761d546e5596c35ceea6e0f34.jpg",
    "synopsis": "Not available",
    "author": [
      "Unknown"
    ],
    "genres": [
      "Action",
      "Comedy",
      "Drama",
      "Sci-Fi",
      "Seinen",
      "Supernatural"
    ],
    "rating": null,
    "status": "Unknown"
  },
  {
    "title": "Tiger & Dragon",
    "url": "https://mangareader.to/tiger-dragon-61822",
    "cover_url": "https://img.mreadercdn.com/_m/300x400/100/f1/59/f1595d27554b81c4297d188d2e76ea95/f1595d27554b81c4297d188d2e76ea95.jpg",
    "synopsis": "Not available",
    "author": [
      "Unknown"
    ],
    "genres": [
      "Comedy",
      "Romance",
      "Shoujo"
    ],
    "rating": null,
    "status": "Unknown"
  },
  {
    "title": "Tiger Coming In",
    "url": "https://mangareader.to/tiger-coming-in-63138",
    "cover_url": "https://img.mreadercdn.com/_m/300x400/100/58/ef/58ef787c8e7af13d3b2bd4f0321f3a9a/58ef787c8e7af13d3b2bd4f0321f3a9a.jpg",
    "synopsis": "Not available",
    "author": [
      "Unknown"
    ],
    "genres": [
      "Comedy",
      "Fantasy",
      "Shoujo",
      "Slice of Life"
    ],
    "rating": null,
    "status": "Unknown"
  },
  {
    "title": "Till Our Lips Touch",
    "url": "https://mangareader.to/till-our-lips-touch-62250",
    "cover_url": "https://img.mreadercdn.com/_m/300x400/100/3f/19/3f199ba3fd5f5b5795a4418118e6e8a5/3f199ba3fd5f5b5795a4418118e6e8a5.jpg",
    "synopsis": "Not available",
    "author": [
      "Unknown"
    ],
    "genres": [
      "Drama",
      "Romance",
      "Yaoi"
    ],
    "rating": null,
    "status": "Unknown"
  },
  {
    "title": "Till The End Of The Moon",
    "url": "https://mangareader.to/till-the-end-of-the-moon-61764",
    "cover_url": "https://img.mreadercdn.com/_m/300x400/100/c0/87/c0872c339dc47367cc45be4bc2714492/c0872c339dc47367cc45be4bc2714492.jpg",
    "synopsis": "Not available",
    "author": [
      "Unknown"
    ],
    "genres": [
      "Fantasy",
      "Historical",
      "Romance"
    ],
    "rating": null,
    "status": "Unknown"
  },
  {
    "title": "Time and Reason",
    "url": "https://mangareader.to/time-and-reason-63534",
    "cover_url": "https://img.mreadercdn.com/_m/300x400/100/55/e0/55e0fc3590761c8147ce6eeff657a0de/55e0fc3590761c8147ce6eeff657a0de.jpg",
    "synopsis": "Not available",
    "author": [
      "Unknown"
    ],
    "genres": [
      "Drama",
      "Romance"
    ],
    "rating": null,
    "status": "Unknown"
  },
  {
    "title": "Time and Time Again",
    "url": "https://mangareader.to/time-and-time-again-62626",
    "cover_url": "https://img.mreadercdn.com/_m/300x400/100/8a/bc/8abc220fb0e8181c6dddbf91a64978e2/8abc220fb0e8181c6dddbf91a64978e2.jpg",
    "synopsis": "Not available",
    "author": [
      "Unknown"
    ],
    "genres": [
      "",
      "Genres\n\n\n\n\n\n\n\n\n⚡\n            Latest Updated\n✌ New Release\n🔥\n            Most Viewed\n✅\n            Completed\n\n\n\nAction\n\n\nAdventure\n\n\nCars\n\n\nComedy\n\n\nDementia\n\n\nDemons\n\n\nDoujinshi\n\n\nDrama\n\n\nEcchi\n\n\nFantasy\n\n\nGame\n\n\nGender Bender\n\n\nHarem\n\n\nHentai\n\n\nHistorical\n\n\nHorror\n\n\nJosei\n\n\nKids\n\n\nMagic\n\n\nMartial Arts\n\n\nMecha\n\n\nMilitary\n\n\nMusic\n\n\nMystery\n\n\nParody\n\n\nPolice\n\n\nPsychological\n\n\nRomance\n\n\nSamurai\n\n\nSchool\n\n\nSci-Fi\n\n\nSeinen\n\n\nShoujo\n\n\nShoujo Ai\n\n\nShounen\n\n\nShounen Ai\n\n\nSlice of Life\n\n\nSpace\n\n\nSports\n\n\nSuper Power\n\n\nSupernatural\n\n\nThriller\n\n\nVampire\n\n\nYaoi\n\n\nYuri\n\n+ More"
    ],
    "rating": null,
    "status": "Unknown"
  },
  {
    "title": "Time for Boy",
    "url": "https://mangareader.to/time-for-boy-59316",
    "cover_url": "https://img.mreadercdn.com/_m/300x400/100/20/67/2067ba9cf435518b8f0dd6f2e3acbd07/2067ba9cf435518b8f0dd6f2e3acbd07.jpg",
    "synopsis": "Not available",
    "author": [
      "Unknown"
    ],
    "genres": [
      "Comedy",
      "Drama",
      "Harem",
      "Romance",
      "Seinen"
    ],
    "rating": null,
    "status": "Unknown"
  },
  {
    "title": "Time Paradox Ghostwriter",
    "url": "https://mangareader.to/time-paradox-ghostwriter-12670",
    "cover_url": "https://img.mreadercdn.com/_m/300x400/100/e3/ed/e3edd1c8f611142fa007871d732107c5/e3edd1c8f611142fa007871d732107c5.jpg",
    "synopsis": "Not available",
    "author": [
      "Unknown"
    ],
    "genres": [
      "Sci-Fi",
      "Shounen",
      "Supernatural"
    ],
    "rating": null,
    "status": "Unknown"
  },
  {
    "title": "Time Roulette",
    "url": "https://mangareader.to/time-roulette-59996",
    "cover_url": "https://img.mreadercdn.com/_m/300x400/100/93/7f/937f2da9e2e6e0a4a88d37e66b087a48/937f2da9e2e6e0a4a88d37e66b087a48.jpg",
    "synopsis": "Not available",
    "author": [
      "Unknown"
    ],
    "genres": [
      "Action",
      "Adventure",
      "Fantasy",
      "Shounen"
    ],
    "rating": null,
    "status": "Unknown"
  },
  {
    "title": "Time Stop Brave",
    "url": "https://mangareader.to/time-stop-brave-9848",
    "cover_url": "https://img.mreadercdn.com/_m/300x400/100/34/0a/340a7ad84c3fb7de1b2e113c2c5b05c0/340a7ad84c3fb7de1b2e113c2c5b05c0.jpg",
    "synopsis": "Not available",
    "author": [
      "Unknown"
    ],
    "genres": [
      "Adventure",
      "Comedy",
      "Ecchi",
      "Fantasy",
      "Shounen"
    ],
    "rating": null,
    "status": "Unknown"
  },
  {
    "title": "Tired of Life, The Strongest Magician Gave up and Fell Asleep",
    "url": "https://mangareader.to/tired-of-life-the-strongest-magician-gave-up-and-fell-asleep-68225",
    "cover_url": "https://img.mreadercdn.com/_m/300x400/100/5e/b0/5eb04235463d37768dc52a8e4c9912d2/5eb04235463d37768dc52a8e4c9912d2.jpg",
    "synopsis": "Not available",
    "author": [
      "Unknown"
    ],
    "genres": [
      "Action",
      "Fantasy",
      "Magic",
      "Romance"
    ],
    "rating": null,
    "status": "Unknown"
  },
  {
    "title": "Tired Of Waiting For Love",
    "url": "https://mangareader.to/tired-of-waiting-for-love-37866",
    "cover_url": "https://img.mreadercdn.com/_m/300x400/100/52/4e/524ea1e58b474461c781799ce2954c3e/524ea1e58b474461c781799ce2954c3e.jpg",
    "synopsis": "Not available",
    "author": [
      "Unknown"
    ],
    "genres": [
      "Drama",
      "Yaoi"
    ],
    "rating": null,
    "status": "Unknown"
  },
  {
    "title": "Tista",
    "url": "https://mangareader.to/tista-6001",
    "cover_url": "https://img.mreadercdn.com/_m/300x400/100/fc/e1/fce1ae0e777c3f3abcb2ebb23ced03c1/fce1ae0e777c3f3abcb2ebb23ced03c1.jpg",
    "synopsis": "Not available",
    "author": [
      "Unknown"
    ],
    "genres": [
      "Action",
      "Drama",
      "Shounen"
    ],
    "rating": null,
    "status": "Unknown"
  },
  {
    "title": "To a New You",
    "url": "https://mangareader.to/to-a-new-you-66699",
    "cover_url": "https://img.mreadercdn.com/_m/300x400/100/22/b6/22b66295ba64399d7039d9baa12514c8/22b66295ba64399d7039d9baa12514c8.jpg",
    "synopsis": "Not available",
    "author": [
      "Unknown"
    ],
    "genres": [
      "Drama",
      "Seinen",
      "Slice of Life"
    ],
    "rating": null,
    "status": "Unknown"
  }
]