[
  {
    "title": "Otonari-San Game",
    "url": "https://mangareader.to/otonari-san-game-8882",
    "cover_url": "https://img.mreadercdn.com/_m/300x400/100/a7/0d/a70d307088085c81cec3ba008e3bcbd0/a70d307088085c81cec3ba008e3bcbd0.jpg",
    "synopsis": "Not available",
    "author": [
      "Unknown"
    ],
    "genres": [
      "Comedy",
      "Romance",
      "Slice of Life"
    ],
    "rating": null,
    "status": "Unknown"
  },
  {
    "title": "Otoshite Kudasai! Megami-sama!!",
    "url": "https://mangareader.to/otoshite-kudasai-megami-sama-57500",
    "cover_url": "https://img.mreadercdn.com/_m/300x400/100/20/b4/20b4e5be7e64f18c7eab43bf119b1279/20b4e5be7e64f18c7eab43bf119b1279.jpg",
    "synopsis": "Not available",
    "author": [
      "Unknown"
    ],
    "genres": [
      "Comedy",
      "Martial Arts",
      "Romance",
      "Shounen"
    ],
    "rating": null,
    "status": "Unknown"
  },
  {
    "title": "Ottoman",
    "url": "https://mangareader.to/ottoman-56058",
    "cover_url": "https://img.mreadercdn.com/_m/300x400/100/dc/da/dcda0d6ae810668f9d36686bcbe4317b/dcda0d6ae810668f9d36686bcbe4317b.jpg",
    "synopsis": "Not available",
    "author": [
      "Unknown"
    ],
    "genres": [
      "Action",
      "Sci-Fi",
      "Seinen"
    ],
    "rating": null,
    "status": "Unknown"
  },
  {
    "title": "Ouhi Margot",
    "url": "https://mangareader.to/ouhi-margot-27286",
    "cover_url": "https://img.mreadercdn.com/_m/300x400/100/14/b7/14b7eeb0b02b401f0fcec2882244ddb6/14b7eeb0b02b401f0fcec2882244ddb6.jpg",
    "synopsis": "Not available",
    "author": [
      "Unknown"
    ],
    "genres": [
      "Historical",
      "Josei"
    ],
    "rating": null,
    "status": "Unknown"
  },
  {
    "title": "Ouji Ka Prince",
    "url": "https://mangareader.to/ouji-ka-prince-8501",
    "cover_url": "https://img.mreadercdn.com/_m/300x400/100/34/43/34438d133022effdffc5dddcc6205df0/34438d133022effdffc5dddcc6205df0.jpg",
    "synopsis": "Not available",
    "author": [
      "Unknown"
    ],
    "genres": [
      "School",
      "Shoujo"
    ],
    "rating": null,
    "status": "Unknown"
  },
  {
    "title": "Ouji-sama wo Tsukamaero!",
    "url": "https://mangareader.to/oujisama-wo-tsukamaero-39525",
    "cover_url": "https://img.mreadercdn.com/_m/300x400/100/43/4e/434ea709e436d0d59734b75eb923a98d/434ea709e436d0d59734b75eb923a98d.jpg",
    "synopsis": "Not available",
    "author": [
      "Unknown"
    ],
    "genres": [
      "Romance",
      "School",
      "Yaoi"
    ],
    "rating": null,
    "status": "Unknown"
  },
  {
    "title": "Oukyuu wo Tsuihousareta Seijo desu ga, Jitsu wa Honmono no Akujo wa Imouto da to Kidzuite mo Mou Osoi – Watashi wa Kachi wo Mitomete Kureru Koushaku to Shiawase ni narimasu",
    "url": "https://mangareader.to/oukyuu-wo-tsuihousareta-seijo-desu-ga-jitsu-wa-honmono-no-akujo-wa-imouto-da-to-kidzuite-mo-mou-osoi-watashi-wa-kachi-wo-mitomete-kureru-koushaku-to-shiawase-ni-narimasu-66161",
    "cover_url": "https://img.mreadercdn.com/_m/300x400/100/2a/90/2a906df2911b804f8fab626e423e5b51/2a906df2911b804f8fab626e423e5b51.jpg",
    "synopsis": "Not available",
    "author": [
      "Unknown"
    ],
    "genres": [
      "Fantasy",
      "Josei",
      "Slice of Life"
    ],
    "rating": null,
    "status": "Unknown"
  },
  {
    "title": "Ouma Kurashi no Yakko-san",
    "url": "https://mangareader.to/ouma-kurashi-no-yakko-san-66323",
    "cover_url": "https://img.mreadercdn.com/_m/300x400/100/aa/45/aa45330cd89741390b1fcdfa6fe152c5/aa45330cd89741390b1fcdfa6fe152c5.jpg",
    "synopsis": "Not available",
    "author": [
      "Unknown"
    ],
    "genres": [
      "Comedy",
      "Slice of Life"
    ],
    "rating": null,
    "status": "Unknown"
  },
  {
    "title": "Oumagadoki Doubutsuen",
    "url": "https://mangareader.to/oumagadoki-doubutsuen-4630",
    "cover_url": "https://img.mreadercdn.com/_m/300x400/100/db/6a/db6a3a07ed72a8526507f4352f70e966/db6a3a07ed72a8526507f4352f70e966.jpg",
    "synopsis": "Not available",
    "author": [
      "Unknown"
    ],
    "genres": [
      "Action",
      "Comedy",
      "Fantasy",
      "Shounen"
    ],
    "rating": null,
    "status": "Unknown"
  },
  {
    "title": "Our Abnormalities",
    "url": "https://mangareader.to/our-abnormalities-1271",
    "cover_url": "https://img.mreadercdn.com/_m/300x400/100/ba/30/ba30cb0db9add1a63953c225a1fe4476/ba30cb0db9add1a63953c225a1fe4476.jpg",
    "synopsis": "Not available",
    "author": [
      "Unknown"
    ],
    "genres": [
      "Drama",
      "Gender Bender",
      "Psychological",
      "Seinen",
      "Shounen Ai"
    ],
    "rating": null,
    "status": "Unknown"
  },
  {
    "title": "Our Banri will be in your care",
    "url": "https://mangareader.to/our-banri-will-be-in-your-care-68033",
    "cover_url": "https://img.mreadercdn.com/_m/300x400/100/b2/e5/b2e51faa70cd5fc6d1ffb371d89c4c97/b2e51faa70cd5fc6d1ffb371d89c4c97.jpg",
    "synopsis": "Not available",
    "author": [
      "Unknown"
    ],
    "genres": [
      "Comedy",
      "Romance",
      "Slice of Life"
    ],
    "rating": null,
    "status": "Unknown"
  },
  {
    "title": "Our Beloved Summer",
    "url": "https://mangareader.to/our-beloved-summer-59380",
    "cover_url": "https://img.mreadercdn.com/_m/300x400/100/d7/49/d74989fccfae301845c32b75ccbe3ba0/d74989fccfae301845c32b75ccbe3ba0.jpg",
    "synopsis": "Not available",
    "author": [
      "Unknown"
    ],
    "genres": [
      "Comedy",
      "Drama",
      "Romance",
      "Shoujo"
    ],
    "rating": null,
    "status": "Unknown"
  },
  {
    "title": "Our Blood Oath",
    "url": "https://mangareader.to/our-blood-oath-13989",
    "cover_url": "https://img.mreadercdn.com/_m/300x400/100/b8/31/b831c73ee6d10588e4535ea06a93125e/b831c73ee6d10588e4535ea06a93125e.jpg",
    "synopsis": "Not available",
    "author": [
      "Unknown"
    ],
    "genres": [
      "Demons",
      "Horror",
      "Shounen",
      "Supernatural",
      "Vampire"
    ],
    "rating": null,
    "status": "Unknown"
  },
  {
    "title": "Our Blooming Love Struggles",
    "url": "https://mangareader.to/our-blooming-love-struggles-58180",
    "cover_url": "https://img.mreadercdn.com/_m/300x400/100/3c/1d/3c1d91361b1a10075f1e34d3a2c6d323/3c1d91361b1a10075f1e34d3a2c6d323.jpg",
    "synopsis": "Not available",
    "author": [
      "Unknown"
    ],
    "genres": [
      "Romance",
      "Slice of Life"
    ],
    "rating": null,
    "status": "Unknown"
  },
  {
    "title": "Our Bodies, Entwining, Entwined",
    "url": "https://mangareader.to/our-bodies-entwining-entwined-62772",
    "cover_url": "https://img.mreadercdn.com/_m/300x400/100/f2/79/f27942c38c2037a292b239702dc0a95b/f27942c38c2037a292b239702dc0a95b.jpg",
    "synopsis": "Not available",
    "author": [
      "Unknown"
    ],
    "genres": [
      "Drama",
      "Romance"
    ],
    "rating": null,
    "status": "Unknown"
  },
  {
    "title": "Our Broken Strategic Love",
    "url": "https://mangareader.to/our-broken-strategic-love-67113",
    "cover_url": "https://img.mreadercdn.com/_m/300x400/100/5c/1c/5c1c4e452d58e6253d39c46c5ec2ba44/5c1c4e452d58e6253d39c46c5ec2ba44.jpg",
    "synopsis": "Not available",
    "author": [
      "Unknown"
    ],
    "genres": [
      "Drama",
      "Romance",
      "School",
      "Slice of Life"
    ],
    "rating": null,
    "status": "Unknown"
  },
  {
    "title": "Our Circumstances At the Bottom of the Hierarchy",
    "url": "https://mangareader.to/our-circumstances-at-the-bottom-of-the-hierarchy-59946",
    "cover_url": "https://img.mreadercdn.com/_m/300x400/100/84/4c/844c4ec031c4e196be6f81b82314ed5e/844c4ec031c4e196be6f81b82314ed5e.jpg",
    "synopsis": "Not available",
    "author": [
      "Unknown"
    ],
    "genres": [
      "Romance",
      "Shoujo",
      "Slice of Life"
    ],
    "rating": null,
    "status": "Unknown"
  },
  {
    "title": "Our Classmates Don’t Know We’re Having Sex In Your Room",
    "url": "https://mangareader.to/our-classmates-dont-know-were-having-sex-in-your-room-66105",
    "cover_url": "https://img.mreadercdn.com/_m/300x400/100/35/65/3565c64a8d70c16ef8b064487182be6e/3565c64a8d70c16ef8b064487182be6e.jpg",
    "synopsis": "Not available",
    "author": [
      "Unknown"
    ],
    "genres": [
      "Comedy",
      "Drama",
      "Ecchi",
      "Romance",
      "School"
    ],
    "rating": null,
    "status": "Unknown"
  }
]