[
  {
    "title": "Mitsu no Miko to Hana no Juusha",
    "url": "https://mangareader.to/mitsu-no-miko-to-hana-no-juusha-67643",
    "cover_url": "https://img.mreadercdn.com/_m/300x400/100/46/b7/46b70260e06e4b2344eb9bd2e3b4b3ef/46b70260e06e4b2344eb9bd2e3b4b3ef.jpg",
    "synopsis": "Not available",
    "author": [
      "Unknown"
    ],
    "genres": [
      "Action",
      "Comedy",
      "Seinen",
      "Slice of Life"
    ],
    "rating": null,
    "status": "Unknown"
  },
  {
    "title": "Mitsuba no Monogatari",
    "url": "https://mangareader.to/mitsuba-no-monogatari-65941",
    "cover_url": "https://img.mreadercdn.com/_m/300x400/100/5a/b7/5ab744ef45f7db77311b78af2a80668c/5ab744ef45f7db77311b78af2a80668c.jpg",
    "synopsis": "Not available",
    "author": [
      "Unknown"
    ],
    "genres": [
      "Fantasy"
    ],
    "rating": null,
    "status": "Unknown"
  },
  {
    "title": "Mitsuishi-san is Being Weird This Year",
    "url": "https://mangareader.to/mitsuishi-san-is-being-weird-this-year-55490",
    "cover_url": "https://img.mreadercdn.com/_m/300x400/100/e1/b9/e1b9227a5d8b84e4f7fb570f6c1da9f6/e1b9227a5d8b84e4f7fb570f6c1da9f6.jpg",
    "synopsis": "Not available",
    "author": [
      "Unknown"
    ],
    "genres": [
      "Comedy",
      "Romance",
      "School",
      "Slice of Life"
    ],
    "rating": null,
    "status": "Unknown"
  },
  {
    "title": "Mitsuru Bocchan wa Bocchi",
    "url": "https://mangareader.to/mitsuru-bocchan-wa-bocchi-58014",
    "cover_url": "https://img.mreadercdn.com/_m/300x400/100/29/3c/293c70262530cfcba8ceb18595c2ee88/293c70262530cfcba8ceb18595c2ee88.jpg",
    "synopsis": "Not available",
    "author": [
      "Unknown"
    ],
    "genres": [
      "Comedy",
      "Drama",
      "Slice of Life"
    ],
    "rating": null,
    "status": "Unknown"
  },
  {
    "title": "Mitsuyokon Tsukumogami no Yomegoryou",
    "url": "https://mangareader.to/mitsuyokon-tsukumogami-no-yomegoryou-2937",
    "cover_url": "https://img.mreadercdn.com/_m/300x400/100/df/9b/df9bf8de3358c8cc6d06943aedd9e72e/df9bf8de3358c8cc6d06943aedd9e72e.jpg",
    "synopsis": "Not available",
    "author": [
      "Unknown"
    ],
    "genres": [
      "Drama",
      "Josei",
      "Romance",
      "Supernatural"
    ],
    "rating": null,
    "status": "Unknown"
  },
  {
    "title": "Mix",
    "url": "https://mangareader.to/mix-1746",
    "cover_url": "https://img.mreadercdn.com/_m/300x400/100/24/3f/243fca90260bde490636ef40710ccfad/243fca90260bde490636ef40710ccfad.jpg",
    "synopsis": "Not available",
    "author": [
      "Unknown"
    ],
    "genres": [
      "Drama",
      "Romance",
      "School",
      "Shounen",
      "Sports"
    ],
    "rating": null,
    "status": "Unknown"
  },
  {
    "title": "Miyu-chan Will Always Be Your Friend",
    "url": "https://mangareader.to/miyu-chan-will-always-be-your-friend-68251",
    "cover_url": "https://img.mreadercdn.com/_m/300x400/100/b6/ee/b6eeb29be978432b012548da0f544045/b6eeb29be978432b012548da0f544045.jpg",
    "synopsis": "Not available",
    "author": [
      "Unknown"
    ],
    "genres": [
      "Comedy",
      "Drama",
      "Mystery",
      "Romance"
    ],
    "rating": null,
    "status": "Unknown"
  },
  {
    "title": "Mizudako-chan kara wa Nigerarenai!",
    "url": "https://mangareader.to/mizudako-chan-kara-wa-nigerarenai-68439",
    "cover_url": "https://img.mreadercdn.com/_m/300x400/100/b3/7a/b37ad5be1ab12631d91ca67d7b4439c7/b37ad5be1ab12631d91ca67d7b4439c7.jpg",
    "synopsis": "Not available",
    "author": [
      "Unknown"
    ],
    "genres": [
      "Comedy",
      "Romance",
      "Slice of Life",
      "Supernatural"
    ],
    "rating": null,
    "status": "Unknown"
  },
  {
    "title": "Mizuki-senpai is Love Fortune-teller",
    "url": "https://mangareader.to/mizukisenpai-is-love-fortuneteller-36852",
    "cover_url": "https://img.mreadercdn.com/_m/300x400/100/a7/78/a7789094e4b191d8f6fb25518fc03aba/a7789094e4b191d8f6fb25518fc03aba.jpg",
    "synopsis": "Not available",
    "author": [
      "Unknown"
    ],
    "genres": [
      "Comedy",
      "Romance",
      "School",
      "Seinen"
    ],
    "rating": null,
    "status": "Unknown"
  },
  {
    "title": "Mizutamari Ni Ukabu Shima",
    "url": "https://mangareader.to/mizutamari-ni-ukabu-shima-35308",
    "cover_url": "https://img.mreadercdn.com/_m/300x400/100/af/fc/affc8351cb534d30ab80f3e94d722ce5/affc8351cb534d30ab80f3e94d722ce5.jpg",
    "synopsis": "Not available",
    "author": [
      "Unknown"
    ],
    "genres": [
      "Drama",
      "Psychological",
      "Seinen"
    ],
    "rating": null,
    "status": "Unknown"
  },
  {
    "title": "Mo Shi Wei Wang",
    "url": "https://mangareader.to/mo-shi-wei-wang-56578",
    "cover_url": "https://img.mreadercdn.com/_m/300x400/100/e5/62/e5620dae3bc97c75e76e2707ecf9820f/e5620dae3bc97c75e76e2707ecf9820f.jpg",
    "synopsis": "Not available",
    "author": [
      "Unknown"
    ],
    "genres": [
      "Action",
      "Adventure",
      "Drama",
      "Fantasy",
      "Romance",
      "Shounen"
    ],
    "rating": null,
    "status": "Unknown"
  },
  {
    "title": "Mob Douzen no Akuyaku Reijou wa Dansou Shite Kouryaku Taishou no Za o Nerau",
    "url": "https://mangareader.to/mob-douzen-no-akuyaku-reijou-wa-dansou-shite-kouryaku-taishou-no-za-o-nerau-63322",
    "cover_url": "https://img.mreadercdn.com/_m/300x400/100/e3/2e/e32e64da8dba56aca3fe05454d0e625e/e32e64da8dba56aca3fe05454d0e625e.jpg",
    "synopsis": "Not available",
    "author": [
      "Unknown"
    ],
    "genres": [
      "Drama",
      "Fantasy",
      "Gender Bender",
      "Historical",
      "Romance",
      "School",
      "Shoujo"
    ],
    "rating": null,
    "status": "Unknown"
  },
  {
    "title": "Mob kara Hajimaru Tansaku Eiyuutan",
    "url": "https://mangareader.to/mob-kara-hajimaru-tansaku-eiyuutan-57874",
    "cover_url": "https://img.mreadercdn.com/_m/300x400/100/14/2b/142bcb15ad59700aa39d2f8c1845e07d/142bcb15ad59700aa39d2f8c1845e07d.jpg",
    "synopsis": "Not available",
    "author": [
      "Unknown"
    ],
    "genres": [
      "Action",
      "Adventure",
      "Comedy",
      "Ecchi",
      "Fantasy",
      "Romance",
      "Seinen"
    ],
    "rating": null,
    "status": "Unknown"
  },
  {
    "title": "Mob nanoni Makikomareteimasu ~ Ouji no Ibukuro wo Tsukandarashi ~",
    "url": "https://mangareader.to/mob-nanoni-makikomareteimasu-ouji-no-ibukuro-wo-tsukandarashi-56734",
    "cover_url": "https://img.mreadercdn.com/_m/300x400/100/09/89/098957700f828437653fba57c513ba91/098957700f828437653fba57c513ba91.jpg",
    "synopsis": "Not available",
    "author": [
      "Unknown"
    ],
    "genres": [
      "Slice of Life"
    ],
    "rating": null,
    "status": "Unknown"
  },
  {
    "title": "Mobile Police Patlabor",
    "url": "https://mangareader.to/mobile-police-patlabor-2375",
    "cover_url": "https://img.mreadercdn.com/_m/300x400/100/b7/0d/b70d8ccb26b59f633bf11a849e13a602/b70d8ccb26b59f633bf11a849e13a602.jpg",
    "synopsis": "Not available",
    "author": [
      "Unknown"
    ],
    "genres": [
      "Action",
      "Comedy",
      "Drama",
      "Mecha",
      "Sci-Fi",
      "Shounen"
    ],
    "rating": null,
    "status": "Unknown"
  },
  {
    "title": "Mobile Suit Cross Born Gundam Dust",
    "url": "https://mangareader.to/mobile-suit-cross-born-gundam-dust-19951",
    "cover_url": "https://img.mreadercdn.com/_m/300x400/100/98/e9/98e9204164df00a6f8edc17b99690897/98e9204164df00a6f8edc17b99690897.jpg",
    "synopsis": "Not available",
    "author": [
      "Unknown"
    ],
    "genres": [
      "Action",
      "Mecha",
      "Sci-Fi",
      "Shounen",
      "Space"
    ],
    "rating": null,
    "status": "Unknown"
  },
  {
    "title": "Mobile Suit Crossbone Gundam: Ghost",
    "url": "https://mangareader.to/mobile-suit-crossbone-gundam-ghost-56670",
    "cover_url": "https://img.mreadercdn.com/_m/300x400/100/e6/9c/e69c433fb20f14ba7d835cf20a962100/e69c433fb20f14ba7d835cf20a962100.jpg",
    "synopsis": "Not available",
    "author": [
      "Unknown"
    ],
    "genres": [
      "Action",
      "Mecha",
      "Sci-Fi",
      "Shounen"
    ],
    "rating": null,
    "status": "Unknown"
  },
  {
    "title": "Mobile Suit Gundam 0080: War in the Pocket",
    "url": "https://mangareader.to/mobile-suit-gundam-0080-war-in-the-pocket-25153",
    "cover_url": "https://img.mreadercdn.com/_m/300x400/100/ba/1b/ba1b34614b02df6d162fd9ce3f377a09/ba1b34614b02df6d162fd9ce3f377a09.jpg",
    "synopsis": "Not available",
    "author": [
      "Unknown"
    ],
    "genres": [
      "Action",
      "Mecha",
      "Sci-Fi",
      "Shounen"
    ],
    "rating": null,
    "status": "Unknown"
  }
]