[
  {
    "title": "Temple: No One Can Live On Loneliness",
    "url": "https://mangareader.to/temple-no-one-can-live-on-loneliness-1954",
    "cover_url": "https://img.mreadercdn.com/_m/300x400/100/6c/43/6c4381dbe63628218b990140597e375c/6c4381dbe63628218b990140597e375c.jpg",
    "synopsis": "Not available",
    "author": [
      "Unknown"
    ],
    "genres": [
      "Comedy",
      "Ecchi",
      "Harem",
      "Romance",
      "Slice of Life"
    ],
    "rating": null,
    "status": "Unknown"
  },
  {
    "title": "Temptation of Shiro Gal & Kuro Ga",
    "url": "https://mangareader.to/temptation-of-shiro-gal-kuro-ga-62286",
    "cover_url": "https://img.mreadercdn.com/_m/300x400/100/09/37/093710a683734e6d5ba95a9c15ec6eb0/093710a683734e6d5ba95a9c15ec6eb0.jpg",
    "synopsis": "Not available",
    "author": [
      "Unknown"
    ],
    "genres": [
      "Comedy",
      "Ecchi",
      "Romance",
      "Seinen",
      "Shoujo Ai"
    ],
    "rating": null,
    "status": "Unknown"
  },
  {
    "title": "Ten Count",
    "url": "https://mangareader.to/ten-count-37404",
    "cover_url": "https://img.mreadercdn.com/_m/300x400/100/3a/1d/3a1d884eb5433c3b9d74f170a4899328/3a1d884eb5433c3b9d74f170a4899328.jpg",
    "synopsis": "Not available",
    "author": [
      "Unknown"
    ],
    "genres": [
      "Drama",
      "Psychological",
      "Romance",
      "Slice of Life"
    ],
    "rating": null,
    "status": "Unknown"
  },
  {
    "title": "Ten Years Later, I Married My Nemesis",
    "url": "https://mangareader.to/ten-years-later-i-married-my-nemesis-61144",
    "cover_url": "https://img.mreadercdn.com/_m/300x400/100/c7/c1/c7c11fa88d0ac9616a726759cae8cdb1/c7c11fa88d0ac9616a726759cae8cdb1.jpg",
    "synopsis": "Not available",
    "author": [
      "Unknown"
    ],
    "genres": [
      "Comedy",
      "Romance",
      "Slice of Life"
    ],
    "rating": null,
    "status": "Unknown"
  },
  {
    "title": "Ten Years Sleeping Princess",
    "url": "https://mangareader.to/ten-years-sleeping-princess-61126",
    "cover_url": "https://img.mreadercdn.com/_m/300x400/100/53/40/5340ea2c7a60e33968731a7b8d573082/5340ea2c7a60e33968731a7b8d573082.jpg",
    "synopsis": "Not available",
    "author": [
      "Unknown"
    ],
    "genres": [
      "Romance",
      "Shoujo"
    ],
    "rating": null,
    "status": "Unknown"
  },
  {
    "title": "Ten: The Blessed Way of the Nice Guy",
    "url": "https://mangareader.to/ten-the-blessed-way-of-the-nice-guy-323",
    "cover_url": "https://img.mreadercdn.com/_m/300x400/100/9f/3e/9f3e15e9e427f002a42ce92b57a66445/9f3e15e9e427f002a42ce92b57a66445.jpg",
    "synopsis": "Not available",
    "author": [
      "Unknown"
    ],
    "genres": [
      "Drama",
      "Game"
    ],
    "rating": null,
    "status": "Unknown"
  },
  {
    "title": "Tenants from Another World",
    "url": "https://mangareader.to/tenants-from-another-world-59558",
    "cover_url": "https://img.mreadercdn.com/_m/300x400/100/53/6e/536e052d2d597f0129d9c3728133876f/536e052d2d597f0129d9c3728133876f.jpg",
    "synopsis": "Not available",
    "author": [
      "Unknown"
    ],
    "genres": [
      "Comedy",
      "Fantasy",
      "Romance"
    ],
    "rating": null,
    "status": "Unknown"
  },
  {
    "title": "Tenchi Mission",
    "url": "https://mangareader.to/tenchi-mission-67015",
    "cover_url": "https://img.mreadercdn.com/_m/300x400/100/c4/15/c41522e1494afaa2d5a64aee26a290e6/c41522e1494afaa2d5a64aee26a290e6.jpg",
    "synopsis": "Not available",
    "author": [
      "Unknown"
    ],
    "genres": [
      "Action",
      "Comedy",
      "Romance"
    ],
    "rating": null,
    "status": "Unknown"
  },
  {
    "title": "Tenchi Muyo! War on Geminar",
    "url": "https://mangareader.to/tenchi-muyo-war-on-geminar-6578",
    "cover_url": "https://img.mreadercdn.com/_m/300x400/100/9e/f7/9ef773f7bcfc099e9055f4766f6826f1/9ef773f7bcfc099e9055f4766f6826f1.jpg",
    "synopsis": "Not available",
    "author": [
      "Unknown"
    ],
    "genres": [
      "Adventure",
      "Drama",
      "Fantasy"
    ],
    "rating": null,
    "status": "Unknown"
  },
  {
    "title": "Tenchura! Tensei Shitara Slime Datta Ken",
    "url": "https://mangareader.to/tenchura-tensei-shitara-slime-datta-ken-5407",
    "cover_url": "https://img.mreadercdn.com/_m/300x400/100/08/4b/084b7ee73e0f23ac643fd5b5dfe0530b/084b7ee73e0f23ac643fd5b5dfe0530b.jpg",
    "synopsis": "Not available",
    "author": [
      "Unknown"
    ],
    "genres": [
      "Adventure",
      "Comedy",
      "Fantasy",
      "Seinen"
    ],
    "rating": null,
    "status": "Unknown"
  },
  {
    "title": "Tengen Hero Wars",
    "url": "https://mangareader.to/tengen-hero-wars-59862",
    "cover_url": "https://img.mreadercdn.com/_m/300x400/100/b8/0d/b80de09cd57a1ce32ef6214b7ee95c49/b80de09cd57a1ce32ef6214b7ee95c49.jpg",
    "synopsis": "Not available",
    "author": [
      "Unknown"
    ],
    "genres": [
      "Action",
      "Adventure",
      "Fantasy",
      "Historical"
    ],
    "rating": null,
    "status": "Unknown"
  },
  {
    "title": "Tengen Toppa Gurren Lagann",
    "url": "https://mangareader.to/tengen-toppa-gurren-lagann-790",
    "cover_url": "https://img.mreadercdn.com/_m/300x400/100/d6/a1/d6a188292c0c78c3ed6ef5ca176d681c/d6a188292c0c78c3ed6ef5ca176d681c.jpg",
    "synopsis": "Not available",
    "author": [
      "Unknown"
    ],
    "genres": [
      "Action",
      "Adventure",
      "Comedy",
      "Mecha",
      "Sci-Fi",
      "Shounen"
    ],
    "rating": null,
    "status": "Unknown"
  },
  {
    "title": "Tengu to Warashi",
    "url": "https://mangareader.to/tengu-to-warashi-57842",
    "cover_url": "https://img.mreadercdn.com/_m/300x400/100/6c/6d/6c6d3e95e18bfa371ec4757c674bcf5b/6c6d3e95e18bfa371ec4757c674bcf5b.jpg",
    "synopsis": "Not available",
    "author": [
      "Unknown"
    ],
    "genres": [
      "",
      "Genres\n\n\n\n\n\n\n\n\n⚡\n            Latest Updated\n✌ New Release\n🔥\n            Most Viewed\n✅\n            Completed\n\n\n\nAction\n\n\nAdventure\n\n\nCars\n\n\nComedy\n\n\nDementia\n\n\nDemons\n\n\nDoujinshi\n\n\nDrama\n\n\nEcchi\n\n\nFantasy\n\n\nGame\n\n\nGender Bender\n\n\nHarem\n\n\nHentai\n\n\nHistorical\n\n\nHorror\n\n\nJosei\n\n\nKids\n\n\nMagic\n\n\nMartial Arts\n\n\nMecha\n\n\nMilitary\n\n\nMusic\n\n\nMystery\n\n\nParody\n\n\nPolice\n\n\nPsychological\n\n\nRomance\n\n\nSamurai\n\n\nSchool\n\n\nSci-Fi\n\n\nSeinen\n\n\nShoujo\n\n\nShoujo Ai\n\n\nShounen\n\n\nShounen Ai\n\n\nSlice of Life\n\n\nSpace\n\n\nSports\n\n\nSuper Power\n\n\nSupernatural\n\n\nThriller\n\n\nVampire\n\n\nYaoi\n\n\nYuri\n\n+ More"
    ],
    "rating": null,
    "status": "Unknown"
  },
  {
    "title": "Tengu's Kitchen",
    "url": "https://mangareader.to/tengus-kitchen-62308",
    "cover_url": "https://img.mreadercdn.com/_m/300x400/100/5d/70/5d703fff98e06f78804c0b6d9d78b6b7/5d703fff98e06f78804c0b6d9d78b6b7.jpg",
    "synopsis": "Not available",
    "author": [
      "Unknown"
    ],
    "genres": [
      "Fantasy",
      "Seinen",
      "Slice of Life"
    ],
    "rating": null,
    "status": "Unknown"
  },
  {
    "title": "Tenisaki wa Kusushi ga Sukunai Sekai Deshita",
    "url": "https://mangareader.to/tenisaki-wa-kusushi-ga-sukunai-sekai-deshita-57752",
    "cover_url": "https://img.mreadercdn.com/_m/300x400/100/bb/ff/bbff087dd1ecf3019d5483522bd3b638/bbff087dd1ecf3019d5483522bd3b638.jpg",
    "synopsis": "Not available",
    "author": [
      "Unknown"
    ],
    "genres": [
      "Fantasy",
      "Romance",
      "Shoujo",
      "Slice of Life"
    ],
    "rating": null,
    "status": "Unknown"
  },
  {
    "title": "Tenka Musou no Otome-tachi ga Ore no Kodane wo Ubaiatteimasu!!!!!",
    "url": "https://mangareader.to/tenka-musou-no-otome-tachi-ga-ore-no-kodane-wo-ubaiatteimasu-66853",
    "cover_url": "https://img.mreadercdn.com/_m/300x400/100/e6/fc/e6fc842aeadf01e81523118fbf0cb462/e6fc842aeadf01e81523118fbf0cb462.jpg",
    "synopsis": "Not available",
    "author": [
      "Unknown"
    ],
    "genres": [
      "Comedy",
      "Ecchi",
      "Harem",
      "Romance"
    ],
    "rating": null,
    "status": "Unknown"
  },
  {
    "title": "Tenkaichi - Nihon Saikyou Bugeisha Ketteisen",
    "url": "https://mangareader.to/tenkaichi-nihon-saikyou-bugeisha-ketteisen-56350",
    "cover_url": "https://img.mreadercdn.com/_m/300x400/100/4b/9f/4b9fade08b9e2f1926e258f1a453a466/4b9fade08b9e2f1926e258f1a453a466.jpg",
    "synopsis": "Not available",
    "author": [
      "Unknown"
    ],
    "genres": [
      "Action",
      "Adventure"
    ],
    "rating": null,
    "status": "Unknown"
  },
  {
    "title": "Tenkaichi: Battle to decide Japan's strongest martial artist",
    "url": "https://mangareader.to/tenkaichi-battle-to-decide-japans-strongest-martial-artist-56722",
    "cover_url": "https://img.mreadercdn.com/_m/300x400/100/ee/be/eebeaa471405ec5b2b6f5b80fc1ab17e/eebeaa471405ec5b2b6f5b80fc1ab17e.jpg",
    "synopsis": "Not available",
    "author": [
      "Unknown"
    ],
    "genres": [
      "Action",
      "Fantasy",
      "Historical",
      "Seinen"
    ],
    "rating": null,
    "status": "Unknown"
  }
]