[
  {
    "title": "Resident Evil: Death Island",
    "url": "https://mangareader.to/resident-evil-death-island-67515",
    "cover_url": "https://img.mreadercdn.com/_m/300x400/100/c1/18/c118bee6644c499ffe79947fa198f94e/c118bee6644c499ffe79947fa198f94e.jpg",
    "synopsis": "Not available",
    "author": [
      "Unknown"
    ],
    "genres": [
      "Action",
      "Drama",
      "Horror",
      "Seinen"
    ],
    "rating": null,
    "status": "Unknown"
  },
  {
    "title": "Resident Evil: Marhawa Desire",
    "url": "https://mangareader.to/resident-evil-marhawa-desire-4445",
    "cover_url": "https://img.mreadercdn.com/_m/300x400/100/85/4e/854e8889cf14915bfa29e59ca1c411a7/854e8889cf14915bfa29e59ca1c411a7.jpg",
    "synopsis": "Not available",
    "author": [
      "Unknown"
    ],
    "genres": [
      "Action",
      "Game",
      "Horror",
      "Military",
      "Shounen"
    ],
    "rating": null,
    "status": "Unknown"
  },
  {
    "title": "Resident Physician of the Brave Party",
    "url": "https://mangareader.to/resident-physician-of-the-brave-party-66999",
    "cover_url": "https://img.mreadercdn.com/_m/300x400/100/f5/2d/f52d7e6aef3f4715a006298bc329dd61/f52d7e6aef3f4715a006298bc329dd61.jpg",
    "synopsis": "Not available",
    "author": [
      "Unknown"
    ],
    "genres": [
      "Comedy",
      "Fantasy",
      "Seinen"
    ],
    "rating": null,
    "status": "Unknown"
  },
  {
    "title": "Resist! Dark Elf-chan",
    "url": "https://mangareader.to/resist-dark-elf-chan-50426",
    "cover_url": "https://img.mreadercdn.com/_m/300x400/100/98/0f/980f696cbf22ffb975ecd20a21593b2c/980f696cbf22ffb975ecd20a21593b2c.jpg",
    "synopsis": "Not available",
    "author": [
      "Unknown"
    ],
    "genres": [
      "Comedy",
      "Fantasy",
      "Shounen"
    ],
    "rating": null,
    "status": "Unknown"
  },
  {
    "title": "Resonance~Way to Become a Novelist~",
    "url": "https://mangareader.to/resonanceway-to-become-a-novelist-2360",
    "cover_url": "https://img.mreadercdn.com/_m/300x400/100/4a/65/4a65580e4a0c4b06cccde0f8cfdbecc0/4a65580e4a0c4b06cccde0f8cfdbecc0.jpg",
    "synopsis": "Not available",
    "author": [
      "Unknown"
    ],
    "genres": [
      "Seinen",
      "Slice of Life"
    ],
    "rating": null,
    "status": "Unknown"
  },
  {
    "title": "Rest assured, Kojizou-kun!",
    "url": "https://mangareader.to/rest-assured-kojizou-kun-58184",
    "cover_url": "https://img.mreadercdn.com/_m/300x400/100/03/8a/038aeaf5b9603a84bfa3f9abff4272ce/038aeaf5b9603a84bfa3f9abff4272ce.jpg",
    "synopsis": "Not available",
    "author": [
      "Unknown"
    ],
    "genres": [
      "Comedy",
      "Kids"
    ],
    "rating": null,
    "status": "Unknown"
  },
  {
    "title": "Restart After Come Back Home",
    "url": "https://mangareader.to/restart-after-come-back-home-1186",
    "cover_url": "https://img.mreadercdn.com/_m/300x400/100/04/d3/04d3a83b771a80c3b7fa45ea82924d0e/04d3a83b771a80c3b7fa45ea82924d0e.jpg",
    "synopsis": "Not available",
    "author": [
      "Unknown"
    ],
    "genres": [
      "Shounen Ai",
      "Slice of Life"
    ],
    "rating": null,
    "status": "Unknown"
  },
  {
    "title": "Restaurant of the Awkward People",
    "url": "https://mangareader.to/restaurant-of-the-awkward-people-61716",
    "cover_url": "https://img.mreadercdn.com/_m/300x400/100/22/e9/22e9d669666d1812aec4acd1fe9ab429/22e9d669666d1812aec4acd1fe9ab429.jpg",
    "synopsis": "Not available",
    "author": [
      "Unknown"
    ],
    "genres": [
      "Comedy",
      "Seinen",
      "Slice of Life"
    ],
    "rating": null,
    "status": "Unknown"
  },
  {
    "title": "Restaurant to Another World",
    "url": "https://mangareader.to/restaurant-to-another-world-2080",
    "cover_url": "https://img.mreadercdn.com/_m/300x400/100/6f/4f/6f4f8a7aa18c1bf6a3aeb52b7e5a6e90/6f4f8a7aa18c1bf6a3aeb52b7e5a6e90.jpg",
    "synopsis": "Not available",
    "author": [
      "Unknown"
    ],
    "genres": [
      "Comedy",
      "Fantasy",
      "Mystery",
      "Seinen"
    ],
    "rating": null,
    "status": "Unknown"
  },
  {
    "title": "Resume",
    "url": "https://mangareader.to/resume-6794",
    "cover_url": "https://img.mreadercdn.com/_m/300x400/100/95/18/9518ddff73eb6966aa32f7c521a3d513/9518ddff73eb6966aa32f7c521a3d513.jpg",
    "synopsis": "Not available",
    "author": [
      "Unknown"
    ],
    "genres": [
      "Josei",
      "Romance",
      "Slice of Life"
    ],
    "rating": null,
    "status": "Unknown"
  },
  {
    "title": "Resurrected Knight trapped in a cursed game",
    "url": "https://mangareader.to/resurrected-knight-trapped-in-a-cursed-game-67037",
    "cover_url": "https://img.mreadercdn.com/_m/300x400/100/cc/03/cc037ef8a91ec449e2cdd10bb3f57cf5/cc037ef8a91ec449e2cdd10bb3f57cf5.jpg",
    "synopsis": "Not available",
    "author": [
      "Unknown"
    ],
    "genres": [
      "Action",
      "Adventure",
      "Fantasy"
    ],
    "rating": null,
    "status": "Unknown"
  },
  {
    "title": "Retaliation of an Unwanted Bride",
    "url": "https://mangareader.to/retaliation-of-an-unwanted-bride-63486",
    "cover_url": "https://img.mreadercdn.com/_m/300x400/100/60/09/6009c605064ef4d2fbad03cb905195f3/6009c605064ef4d2fbad03cb905195f3.jpg",
    "synopsis": "Not available",
    "author": [
      "Unknown"
    ],
    "genres": [
      "Romance"
    ],
    "rating": null,
    "status": "Unknown"
  },
  {
    "title": "Retired puppeteer's MMO epic",
    "url": "https://mangareader.to/retired-puppeteers-mmo-epic-58238",
    "cover_url": "https://img.mreadercdn.com/_m/300x400/100/83/2b/832b6e02abbd6fd0ee3b5aaab96bc884/832b6e02abbd6fd0ee3b5aaab96bc884.jpg",
    "synopsis": "Not available",
    "author": [
      "Unknown"
    ],
    "genres": [
      "Action",
      "Fantasy"
    ],
    "rating": null,
    "status": "Unknown"
  },
  {
    "title": "Reto the Protector",
    "url": "https://mangareader.to/reto-the-protector-68129",
    "cover_url": "https://img.mreadercdn.com/_m/300x400/100/0e/81/0e8125bc27c3091d9d6cd0c78952ccce/0e8125bc27c3091d9d6cd0c78952ccce.jpg",
    "synopsis": "Not available",
    "author": [
      "Unknown"
    ],
    "genres": [
      "Action",
      "Drama",
      "Supernatural"
    ],
    "rating": null,
    "status": "Unknown"
  },
  {
    "title": "Retoroge",
    "url": "https://mangareader.to/retoroge-67487",
    "cover_url": "https://img.mreadercdn.com/_m/300x400/100/66/fc/66fcbc7d009f3099eec5edfd1a559091/66fcbc7d009f3099eec5edfd1a559091.jpg",
    "synopsis": "Not available",
    "author": [
      "Unknown"
    ],
    "genres": [
      "Comedy",
      "School",
      "Seinen",
      "Slice of Life"
    ],
    "rating": null,
    "status": "Unknown"
  },
  {
    "title": "Retouching Of The Night",
    "url": "https://mangareader.to/retouching-of-the-night-65819",
    "cover_url": "https://img.mreadercdn.com/_m/300x400/100/5f/f7/5ff778228caade1ac05b7617b2c36257/5ff778228caade1ac05b7617b2c36257.png",
    "synopsis": "Not available",
    "author": [
      "Unknown"
    ],
    "genres": [
      "Romance"
    ],
    "rating": null,
    "status": "Unknown"
  },
  {
    "title": "Retropolis Scratch",
    "url": "https://mangareader.to/retropolis-scratch-66945",
    "cover_url": "https://img.mreadercdn.com/_m/300x400/100/7c/20/7c204cebbbc8e2ab365af98375c86069/7c204cebbbc8e2ab365af98375c86069.jpg",
    "synopsis": "Not available",
    "author": [
      "Unknown"
    ],
    "genres": [
      "Action",
      "Shounen"
    ],
    "rating": null,
    "status": "Unknown"
  },
  {
    "title": "Retry Juliet",
    "url": "https://mangareader.to/retry-juliet-61122",
    "cover_url": "https://img.mreadercdn.com/_m/300x400/100/fa/d8/fad8fd55a6fc8f402da767b523a2e1ec/fad8fd55a6fc8f402da767b523a2e1ec.jpg",
    "synopsis": "Not available",
    "author": [
      "Unknown"
    ],
    "genres": [
      "Comedy",
      "Romance",
      "Shoujo"
    ],
    "rating": null,
    "status": "Unknown"
  }
]