[
  {
    "title": "Cells at Work! Lady",
    "url": "https://mangareader.to/cells-at-work-lady-36968",
    "cover_url": "https://img.mreadercdn.com/_m/300x400/100/9c/43/9c43b672080c288272f95cebc424bd23/9c43b672080c288272f95cebc424bd23.jpg",
    "synopsis": "Not available",
    "author": [
      "Unknown"
    ],
    "genres": [
      "Comedy",
      "Seinen"
    ],
    "rating": null,
    "status": "Unknown"
  },
  {
    "title": "Cells at Work! Neo Bacteria!",
    "url": "https://mangareader.to/cells-at-work-neo-bacteria-44701",
    "cover_url": "https://img.mreadercdn.com/_m/300x400/100/d1/4e/d14e2e49021087f939199587a5133598/d14e2e49021087f939199587a5133598.jpg",
    "synopsis": "Not available",
    "author": [
      "Unknown"
    ],
    "genres": [
      "Action",
      "Comedy",
      "Shoujo"
    ],
    "rating": null,
    "status": "Unknown"
  },
  {
    "title": "Cells at Work! White Brigade",
    "url": "https://mangareader.to/cells-at-work-white-brigade-36969",
    "cover_url": "https://img.mreadercdn.com/_m/300x400/100/f3/2c/f32cd7f47e8c09b763d2ee3a69befa21/f32cd7f47e8c09b763d2ee3a69befa21.jpg",
    "synopsis": "Not available",
    "author": [
      "Unknown"
    ],
    "genres": [
      "Action",
      "Comedy",
      "Shounen"
    ],
    "rating": null,
    "status": "Unknown"
  },
  {
    "title": "Cells at Work: Bacteria!",
    "url": "https://mangareader.to/cells-at-work-bacteria-32431",
    "cover_url": "https://img.mreadercdn.com/_m/300x400/100/61/73/6173170133e83bef3fda6deb40c83a06/6173170133e83bef3fda6deb40c83a06.jpg",
    "synopsis": "Not available",
    "author": [
      "Unknown"
    ],
    "genres": [
      "Action",
      "Comedy",
      "Shoujo"
    ],
    "rating": null,
    "status": "Unknown"
  },
  {
    "title": "Cells that Don't Work",
    "url": "https://mangareader.to/cells-that-dont-work-33976",
    "cover_url": "https://img.mreadercdn.com/_m/300x400/100/61/82/618272948185f87e556a512f62c0424a/618272948185f87e556a512f62c0424a.jpg",
    "synopsis": "Not available",
    "author": [
      "Unknown"
    ],
    "genres": [
      "Comedy",
      "Shounen"
    ],
    "rating": null,
    "status": "Unknown"
  },
  {
    "title": "Centuria",
    "url": "https://mangareader.to/centuria-68059",
    "cover_url": "https://img.mreadercdn.com/_m/300x400/100/0f/90/0f909088e9b609cc887f3f09279b024e/0f909088e9b609cc887f3f09279b024e.jpg",
    "synopsis": "Not available",
    "author": [
      "Unknown"
    ],
    "genres": [
      "Action",
      "Fantasy"
    ],
    "rating": null,
    "status": "Unknown"
  },
  {
    "title": "CEO Above, Me Below",
    "url": "https://mangareader.to/ceo-above-me-below-59928",
    "cover_url": "https://img.mreadercdn.com/_m/300x400/100/77/ee/77ee8d25821e1c67794eb7c932d96dbf/77ee8d25821e1c67794eb7c932d96dbf.jpg",
    "synopsis": "Not available",
    "author": [
      "Unknown"
    ],
    "genres": [
      "Drama",
      "Josei",
      "Romance"
    ],
    "rating": null,
    "status": "Unknown"
  },
  {
    "title": "Cerberus",
    "url": "https://mangareader.to/cerberus-10563",
    "cover_url": "https://img.mreadercdn.com/_m/300x400/100/3d/ab/3dabe800d76d4bfca4626a3046e826ea/3dabe800d76d4bfca4626a3046e826ea.jpg",
    "synopsis": "Not available",
    "author": [
      "Unknown"
    ],
    "genres": [
      "Action",
      "Shounen",
      "Supernatural"
    ],
    "rating": null,
    "status": "Unknown"
  },
  {
    "title": "Cerberus Jam",
    "url": "https://mangareader.to/cerberus-jam-11664",
    "cover_url": "https://img.mreadercdn.com/_m/300x400/100/88/f4/88f4b533da195c2e56c807bcde94a4b6/88f4b533da195c2e56c807bcde94a4b6.jpg",
    "synopsis": "Not available",
    "author": [
      "Unknown"
    ],
    "genres": [
      "Shounen",
      "Supernatural",
      "Vampire"
    ],
    "rating": null,
    "status": "Unknown"
  },
  {
    "title": "Ceres: Celestial Legend",
    "url": "https://mangareader.to/ceres-celestial-legend-1980",
    "cover_url": "https://img.mreadercdn.com/_m/300x400/100/3c/0a/3c0a481418df66a3796b76ab630bc7e2/3c0a481418df66a3796b76ab630bc7e2.jpg",
    "synopsis": "Not available",
    "author": [
      "Unknown"
    ],
    "genres": [
      "Drama",
      "Fantasy",
      "Harem",
      "Mystery",
      "Romance",
      "Sci-Fi",
      "Shoujo",
      "Supernatural"
    ],
    "rating": null,
    "status": "Unknown"
  },
  {
    "title": "Cesare",
    "url": "https://mangareader.to/cesare-674",
    "cover_url": "https://img.mreadercdn.com/_m/300x400/100/9c/fd/9cfd0368e67c4604dc97b4018b5248a9/9cfd0368e67c4604dc97b4018b5248a9.jpg",
    "synopsis": "Not available",
    "author": [
      "Unknown"
    ],
    "genres": [
      "Drama",
      "Historical",
      "Seinen"
    ],
    "rating": null,
    "status": "Unknown"
  },
  {
    "title": "Cestus",
    "url": "https://mangareader.to/cestus-2553",
    "cover_url": "https://img.mreadercdn.com/_m/300x400/100/28/9f/289fc93041c909e881891018218084a6/289fc93041c909e881891018218084a6.jpg",
    "synopsis": "Not available",
    "author": [
      "Unknown"
    ],
    "genres": [
      "Action",
      "Drama",
      "Historical",
      "Seinen"
    ],
    "rating": null,
    "status": "Unknown"
  },
  {
    "title": "Cestvs Series Volume II: Legend of Desperate Struggle",
    "url": "https://mangareader.to/cestvs-series-volume-ii-legend-of-desperate-struggle-4451",
    "cover_url": "https://img.mreadercdn.com/_m/300x400/100/c0/61/c06154fc78e537e8338f58918bb5dd8a/c06154fc78e537e8338f58918bb5dd8a.jpg",
    "synopsis": "Not available",
    "author": [
      "Unknown"
    ],
    "genres": [
      "Action",
      "Drama",
      "Historical",
      "Seinen"
    ],
    "rating": null,
    "status": "Unknown"
  },
  {
    "title": "Cha! Chu! Cho!",
    "url": "https://mangareader.to/cha-chu-cho-13483",
    "cover_url": "https://img.mreadercdn.com/_m/300x400/100/a7/4f/a74fd63eb456c9ca436a0dfddb59a5e3/a74fd63eb456c9ca436a0dfddb59a5e3.jpg",
    "synopsis": "Not available",
    "author": [
      "Unknown"
    ],
    "genres": [
      "Slice of Life"
    ],
    "rating": null,
    "status": "Unknown"
  },
  {
    "title": "Cha-K-Ra",
    "url": "https://mangareader.to/chakra-40673",
    "cover_url": "https://img.mreadercdn.com/_m/300x400/100/05/69/0569a8506a04d32f76294482baa2e51a/0569a8506a04d32f76294482baa2e51a.jpg",
    "synopsis": "Not available",
    "author": [
      "Unknown"
    ],
    "genres": [
      "Supernatural",
      "Yaoi"
    ],
    "rating": null,
    "status": "Unknown"
  },
  {
    "title": "Chagecha",
    "url": "https://mangareader.to/chagecha-13929",
    "cover_url": "https://img.mreadercdn.com/_m/300x400/100/6b/70/6b704eb3cde73de80902817850807c3a/6b704eb3cde73de80902817850807c3a.jpg",
    "synopsis": "Not available",
    "author": [
      "Unknown"
    ],
    "genres": [
      "Action",
      "Comedy",
      "Shounen"
    ],
    "rating": null,
    "status": "Unknown"
  },
  {
    "title": "Chaika: The Coffin Princess",
    "url": "https://mangareader.to/chaika-the-coffin-princess-4945",
    "cover_url": "https://img.mreadercdn.com/_m/300x400/100/66/06/66061a4f07469c071156b8226b64fc4c/66061a4f07469c071156b8226b64fc4c.jpg",
    "synopsis": "Not available",
    "author": [
      "Unknown"
    ],
    "genres": [
      "Action",
      "Adventure",
      "Comedy",
      "Fantasy",
      "Romance",
      "Shounen"
    ],
    "rating": null,
    "status": "Unknown"
  },
  {
    "title": "Chain Chronicle Crimson",
    "url": "https://mangareader.to/chain-chronicle-crimson-30723",
    "cover_url": "https://img.mreadercdn.com/_m/300x400/100/21/0f/210f18920175e363d376a782e71fa769/210f18920175e363d376a782e71fa769.jpg",
    "synopsis": "Not available",
    "author": [
      "Unknown"
    ],
    "genres": [
      "Action",
      "Fantasy",
      "Magic",
      "Shounen"
    ],
    "rating": null,
    "status": "Unknown"
  }
]