[
  {
    "title": "Kubo-San Doesn't Leave Me Be (A Mob)",
    "url": "https://mangareader.to/kubo-san-doesnt-leave-me-be-a-mob-869",
    "cover_url": "https://img.mreadercdn.com/_m/300x400/100/11/e5/11e526e26ff1b5c8dcd20d0a687bc534/11e526e26ff1b5c8dcd20d0a687bc534.jpg",
    "synopsis": "Not available",
    "author": [
      "Unknown"
    ],
    "genres": [
      "Comedy",
      "Romance",
      "School",
      "Seinen"
    ],
    "rating": null,
    "status": "Unknown"
  },
  {
    "title": "Kuchidome No Gohoubi Wa Dansou Otome To Icha Ero Desu!",
    "url": "https://mangareader.to/kuchidome-no-gohoubi-wa-dansou-otome-to-icha-ero-desu-47356",
    "cover_url": "https://img.mreadercdn.com/_m/300x400/100/b3/2b/b32bfc857c74bc09ecb8cc52737608c8/b32bfc857c74bc09ecb8cc52737608c8.jpg",
    "synopsis": "Not available",
    "author": [
      "Unknown"
    ],
    "genres": [
      "Ecchi",
      "Hentai"
    ],
    "rating": null,
    "status": "Unknown"
  },
  {
    "title": "Kuchiutsusu",
    "url": "https://mangareader.to/kuchiutsusu-33548",
    "cover_url": "https://img.mreadercdn.com/_m/300x400/100/4e/7a/4e7a8508432ccb1c78e8a20587825d21/4e7a8508432ccb1c78e8a20587825d21.jpg",
    "synopsis": "Not available",
    "author": [
      "Unknown"
    ],
    "genres": [
      "Drama",
      "Josei",
      "Romance",
      "Slice of Life"
    ],
    "rating": null,
    "status": "Unknown"
  },
  {
    "title": "Kufujin Rosa wa Kage kara Ai wo Mimamoritai",
    "url": "https://mangareader.to/kufujin-rosa-wa-kage-kara-ai-wo-mimamoritai-65607",
    "cover_url": "https://img.mreadercdn.com/_m/300x400/100/ba/61/ba61d08d4115a45ccad4f650c9274206/ba61d08d4115a45ccad4f650c9274206.jpg",
    "synopsis": "Not available",
    "author": [
      "Unknown"
    ],
    "genres": [
      "Comedy",
      "Fantasy",
      "Historical",
      "Romance"
    ],
    "rating": null,
    "status": "Unknown"
  },
  {
    "title": "Kujima Utaeba Ie Hororo",
    "url": "https://mangareader.to/kujima-utaeba-ie-hororo-60548",
    "cover_url": "https://img.mreadercdn.com/_m/300x400/100/97/0c/970c83979c4ae386de7b7a8448013532/970c83979c4ae386de7b7a8448013532.jpg",
    "synopsis": "Not available",
    "author": [
      "Unknown"
    ],
    "genres": [
      "Comedy",
      "Fantasy",
      "Slice of Life"
    ],
    "rating": null,
    "status": "Unknown"
  },
  {
    "title": "Kujou's Deadly Sins",
    "url": "https://mangareader.to/kujous-deadly-sins-36534",
    "cover_url": "https://img.mreadercdn.com/_m/300x400/100/e1/4b/e14bd2014f971ab9f488b71accf33839/e14bd2014f971ab9f488b71accf33839.jpg",
    "synopsis": "Not available",
    "author": [
      "Unknown"
    ],
    "genres": [
      "Drama",
      "Psychological",
      "Seinen"
    ],
    "rating": null,
    "status": "Unknown"
  },
  {
    "title": "Kuma Bear Gaiden",
    "url": "https://mangareader.to/kuma-bear-gaiden-65671",
    "cover_url": "https://img.mreadercdn.com/_m/300x400/100/35/c8/35c8f9c8b850e879a386fee04d4f7663/35c8f9c8b850e879a386fee04d4f7663.jpg",
    "synopsis": "Not available",
    "author": [
      "Unknown"
    ],
    "genres": [
      "Adventure",
      "Comedy",
      "Fantasy",
      "Mystery"
    ],
    "rating": null,
    "status": "Unknown"
  },
  {
    "title": "Kuma Kuma Kuma Bear",
    "url": "https://mangareader.to/kuma-kuma-kuma-bear-2316",
    "cover_url": "https://img.mreadercdn.com/_m/300x400/100/87/c6/87c6661b221ceb2fd4efac883e8d1ea4/87c6661b221ceb2fd4efac883e8d1ea4.jpg",
    "synopsis": "Not available",
    "author": [
      "Unknown"
    ],
    "genres": [
      "Action",
      "Comedy",
      "Fantasy"
    ],
    "rating": null,
    "status": "Unknown"
  },
  {
    "title": "Kuma: Kuma Weather Today",
    "url": "https://mangareader.to/kuma-kuma-weather-today-16728",
    "cover_url": "https://img.mreadercdn.com/_m/300x400/100/a1/dd/a1dd57a697b91b94af2c0aeda90c2fa3/a1dd57a697b91b94af2c0aeda90c2fa3.jpg",
    "synopsis": "Not available",
    "author": [
      "Unknown"
    ],
    "genres": [
      "Comedy",
      "Fantasy",
      "Slice of Life"
    ],
    "rating": null,
    "status": "Unknown"
  },
  {
    "title": "Kung Fu Boy Legends",
    "url": "https://mangareader.to/kung-fu-boy-legends-1655",
    "cover_url": "https://img.mreadercdn.com/_m/300x400/100/51/df/51dfb79435c12fe74a2e6410443d3310/51dfb79435c12fe74a2e6410443d3310.jpg",
    "synopsis": "Not available",
    "author": [
      "Unknown"
    ],
    "genres": [
      "Action",
      "Adventure",
      "Comedy",
      "Historical",
      "Martial Arts",
      "Shounen"
    ],
    "rating": null,
    "status": "Unknown"
  },
  {
    "title": "Kunigei: Okuni University Art Department Film Program",
    "url": "https://mangareader.to/kunigei-okuni-university-art-department-film-program-68199",
    "cover_url": "https://img.mreadercdn.com/_m/300x400/100/a8/8c/a88c22cd2d6fd219a5b9589f0bda7786/a88c22cd2d6fd219a5b9589f0bda7786.jpg",
    "synopsis": "Not available",
    "author": [
      "Unknown"
    ],
    "genres": [
      "Drama"
    ],
    "rating": null,
    "status": "Unknown"
  },
  {
    "title": "Kunihachibu",
    "url": "https://mangareader.to/kunihachibu-33100",
    "cover_url": "https://img.mreadercdn.com/_m/300x400/100/99/18/9918d79f020df619aa405cf44a974a27/9918d79f020df619aa405cf44a974a27.jpg",
    "synopsis": "Not available",
    "author": [
      "Unknown"
    ],
    "genres": [
      "Shounen",
      "Thriller"
    ],
    "rating": null,
    "status": "Unknown"
  },
  {
    "title": "Kunimitsu No Matsuri",
    "url": "https://mangareader.to/kunimitsu-no-matsuri-15590",
    "cover_url": "https://img.mreadercdn.com/_m/300x400/100/70/81/7081ebc89091404e572c6452c1821825/7081ebc89091404e572c6452c1821825.jpg",
    "synopsis": "Not available",
    "author": [
      "Unknown"
    ],
    "genres": [
      "Action",
      "Comedy",
      "Drama",
      "Shounen"
    ],
    "rating": null,
    "status": "Unknown"
  },
  {
    "title": "Kuno Chiyo The Precog",
    "url": "https://mangareader.to/kuno-chiyo-the-precog-4823",
    "cover_url": "https://img.mreadercdn.com/_m/300x400/100/7d/be/7dbea2ca41b4ab4369a0acd6d0a99b22/7dbea2ca41b4ab4369a0acd6d0a99b22.jpg",
    "synopsis": "Not available",
    "author": [
      "Unknown"
    ],
    "genres": [
      "Comedy",
      "Romance",
      "School",
      "Slice of Life"
    ],
    "rating": null,
    "status": "Unknown"
  },
  {
    "title": "Kunoichi No Ichi",
    "url": "https://mangareader.to/kunoichi-no-ichi-12873",
    "cover_url": "https://img.mreadercdn.com/_m/300x400/100/06/b6/06b68bb4264850998362a6b8153bd35f/06b68bb4264850998362a6b8153bd35f.jpg",
    "synopsis": "Not available",
    "author": [
      "Unknown"
    ],
    "genres": [
      "Ecchi",
      "Harem",
      "School",
      "Seinen",
      "Supernatural"
    ],
    "rating": null,
    "status": "Unknown"
  },
  {
    "title": "Kunoichi no Ichi! no Ni",
    "url": "https://mangareader.to/kunoichi-no-ichi-no-ni-33895",
    "cover_url": "https://img.mreadercdn.com/_m/300x400/100/47/b4/47b47a8b23fe6d2d5513f921e25dd73b/47b47a8b23fe6d2d5513f921e25dd73b.jpg",
    "synopsis": "Not available",
    "author": [
      "Unknown"
    ],
    "genres": [
      "Action",
      "Ecchi",
      "Gender Bender",
      "Harem",
      "Seinen",
      "Super Power",
      "Supernatural"
    ],
    "rating": null,
    "status": "Unknown"
  },
  {
    "title": "Kunon the Sorcerer Can See Through",
    "url": "https://mangareader.to/kunon-the-sorcerer-can-see-through-60722",
    "cover_url": "https://img.mreadercdn.com/_m/300x400/100/b6/58/b6586e742675e075cd742f651652ce08/b6586e742675e075cd742f651652ce08.jpg",
    "synopsis": "Not available",
    "author": [
      "Unknown"
    ],
    "genres": [
      "Fantasy"
    ],
    "rating": null,
    "status": "Unknown"
  },
  {
    "title": "Kurasu no daikirai na joshi to kekkon suru koto ni natta",
    "url": "https://mangareader.to/kurasu-no-daikirai-na-joshi-to-kekkon-suru-koto-ni-natta-50371",
    "cover_url": "https://img.mreadercdn.com/_m/300x400/100/3c/2e/3c2e829d4c9de8343aa251c640b834c4/3c2e829d4c9de8343aa251c640b834c4.jpg",
    "synopsis": "Not available",
    "author": [
      "Unknown"
    ],
    "genres": [
      "Comedy",
      "Romance"
    ],
    "rating": null,
    "status": "Unknown"
  }
]